notedown/__init__.py
notedown/contentsmanager.py
notedown/main.py
notedown/notedown.py
notedown/templates/markdown.tpl
notedown/templates/markdown_outputs.tpl
notedown-1.5.1.dist-info/DESCRIPTION.rst
notedown-1.5.1.dist-info/METADATA
notedown-1.5.1.dist-info/RECORD
notedown-1.5.1.dist-info/WHEEL
notedown-1.5.1.dist-info/entry_points.txt
notedown-1.5.1.dist-info/metadata.json
notedown-1.5.1.dist-info/top_level.txt
