Metadata-Version: 1.0
Name: notedown
Version: 1.5.1
Summary: Convert markdown to IPython notebook.
Home-page: http://github.com/aaren/notedown
Author: Aaron O'Leary
Author-email: dev@aaren.me
License: BSD 2-Clause
Platform: UNKNOWN
